blabel/Blabel.py
blabel/__init__.py
blabel/label_tools.py
blabel/tools.py
blabel/version.py
blabel/data/print_template.html
blabel-0.1.7.dist-info/licenses/LICENCE.txt
examples/barcode_and_dynamic_picture/barcode_and_dynamic_picture.py
examples/labels_from_spreadsheet/labels_from_spreadsheet.py
examples/labels_on_a4_paper/labels_on_a4_paper.py
examples/logo_and_datamatrix/logo_and_datamatrix.py
examples/qrcode_and_date/qrcode_and_date.py
examples/several_items_per_page/several_items_per_page.py
tests/test_samples.py
blabel-0.1.7.dist-info/METADATA
blabel-0.1.7.dist-info/WHEEL
blabel-0.1.7.dist-info/top_level.txt
blabel-0.1.7.dist-info/RECORD
