Metadata-Version: 2.4
Name: blabel
Version: 0.1.7
Summary: Generate multi-page, multi-label PDF files in Python.
Author: Zulko
License-Expression: MIT
Project-URL: Homepage, https://github.com/Edinburgh-Genome-Foundry/blabel
Keywords: label,barcode,pdf,generator
License-File: LICENCE.txt
Requires-Dist: jinja2
Requires-Dist: qrcode
Requires-Dist: pystrich
Requires-Dist: python-barcode
Requires-Dist: pillow
Requires-Dist: weasyprint
Dynamic: license-file
